varutils/__init__.py
varutils/errors.py
varutils/logging.py
varutils/plugs/__init__.py
varutils/plugs/constants.py
varutils/plugs/functional.py
varutils/py.typed
varutils/types.py
varutils/typing.py
varutils-0.0.8.dist-info/LICENSE
varutils-0.0.8.dist-info/WHEEL
varutils-0.0.8.dist-info/METADATA
varutils-0.0.8.dist-info/RECORD
